pytest_randomly/__init__.py
pytest_randomly/py.typed
pytest_randomly-4.0.0.dist-info/licenses/LICENSE
pytest_randomly-4.0.0.dist-info/METADATA
pytest_randomly-4.0.0.dist-info/WHEEL
pytest_randomly-4.0.0.dist-info/entry_points.txt
pytest_randomly-4.0.0.dist-info/top_level.txt
pytest_randomly-4.0.0.dist-info/RECORD
