Metadata-Version: 2.4
Name: pytest-randomly
Version: 4.0.0
Summary: Pytest plugin to randomly order tests and control random.seed.
Author-email: Adam Johnson <me@adamj.eu>
License-Expression: MIT
Project-URL: Changelog, https://github.com/pytest-dev/pytest-randomly/blob/main/CHANGELOG.rst
Project-URL: Funding, https://adamj.eu/books/
Project-URL: Repository, https://github.com/pytest-dev/pytest-randomly
Keywords: pytest,random,randomise,randomize,randomly
Classifier: Development Status :: 5 - Production/Stable
Classifier: Framework :: Pytest
Classifier: Intended Audience :: Developers
Classifier: Natural Language :: English
Classifier: Programming Language :: Python :: 3 :: Only
Classifier: Programming Language :: Python :: 3.9
Classifier: Programming Language :: Python :: 3.10
Classifier: Programming Language :: Python :: 3.11
Classifier: Programming Language :: Python :: 3.12
Classifier: Programming Language :: Python :: 3.13
Classifier: Programming Language :: Python :: 3.14
Classifier: Typing :: Typed
Requires-Python: >=3.9
License-File: LICENSE
Requires-Dist: importlib-metadata>=3.6; python_version < "3.10"
Requires-Dist: pytest
Dynamic: license-file
